gh_action_poc_pssingh21/__init__.py
gh_action_poc_pssingh21/hello_world.py
gh_action_poc_pssingh21-0.1.7.dist-info/METADATA
gh_action_poc_pssingh21-0.1.7.dist-info/WHEEL
gh_action_poc_pssingh21-0.1.7.dist-info/licenses/LICENSE
gh_action_poc_pssingh21-0.1.7.dist-info/RECORD
