Metadata-Version: 2.1
Name: gh_action_poc_pssingh21
Version: 0.1.7
Summary: Github actions for Python package
Project-URL: Homepage, https://github.com/pssingh21/gh-action
Project-URL: Bug Tracker, https://github.com/pssingh21/gh-action/issues
Author-email: Peeyush Singh <peeyush.singh@mhp.com>
License-File: LICENSE
Classifier: License :: OSI Approved :: MIT License
Classifier: Operating System :: OS Independent
Classifier: Programming Language :: Python :: 3
Requires-Python: >=3.7
